riot_na-4.0.7.dist-info/METADATA
riot_na-4.0.7.dist-info/WHEEL
riot_na-4.0.7.dist-info/entry_points.txt
riot_na-4.0.7.dist-info/licenses/LICENSE.txt
riot_na/__init__.py
riot_na/airr/__init__.py
riot_na/airr/airr_builder.py
riot_na/airr/airr_builder_aa.py
riot_na/airr/airr_validator.py
riot_na/alignment/aa_gene_alignments.py
riot_na/alignment/alignment_metrics.py
riot_na/alignment/alignment_utils.py
riot_na/alignment/gene_aligner.py
riot_na/alignment/nt_gene_alignments.py
riot_na/alignment/segment_gene_aligner.py
riot_na/alignment/skbio_alignment.py
riot_na/api/__init__.py
riot_na/api/api_mp.py
riot_na/api/riot_numbering.py
riot_na/api/utils.py
riot_na/cli.py
riot_na/common/__init__.py
riot_na/common/airr_csv_writer.py
riot_na/common/assert_never.py
riot_na/common/debug_utils.py
riot_na/common/gene_match_utils.py
riot_na/common/io.py
riot_na/common/multi_species_prefiltering.py
riot_na/common/multi_species_segment_prefiltering.py
riot_na/common/serialization_utils.py
riot_na/config.py
riot_na/data/__init__.py
riot_na/data/constants.py
riot_na/data/model.py
riot_na/data/scheme_definitions.py
riot_na/data/scheme_mapping_facade.py
riot_na/data/scheme_regions.py
riot_na/databases/gene_db/aa_genes/c_genes/alpaca/igh.fasta
riot_na/databases/gene_db/aa_genes/c_genes/human/igh.fasta
riot_na/databases/gene_db/aa_genes/c_genes/human/igk.fasta
riot_na/databases/gene_db/aa_genes/c_genes/human/igl.fasta
riot_na/databases/gene_db/aa_genes/j_genes/alpaca/igh.fasta
riot_na/databases/gene_db/aa_genes/j_genes/human/igh.fasta
riot_na/databases/gene_db/aa_genes/j_genes/human/igk.fasta
riot_na/databases/gene_db/aa_genes/j_genes/human/igl.fasta
riot_na/databases/gene_db/aa_genes/j_genes/mouse/igh.fasta
riot_na/databases/gene_db/aa_genes/j_genes/mouse/igk.fasta
riot_na/databases/gene_db/aa_genes/j_genes/mouse/igl.fasta
riot_na/databases/gene_db/aa_genes/v_genes/all_species.fasta
riot_na/databases/gene_db/aa_genes/v_genes/alpaca.fasta
riot_na/databases/gene_db/aa_genes/v_genes/human.fasta
riot_na/databases/gene_db/aa_genes/v_genes/mouse.fasta
riot_na/databases/gene_db/aa_genes_deduplicated/c_genes/alpaca/igh.fasta
riot_na-4.0.7.dist-info/RECORD
