Metadata-Version: 2.4
Name: riot_na
Version: 4.0.7
Classifier: Programming Language :: Rust
Classifier: Programming Language :: Python :: Implementation :: CPython
Requires-Dist: biopython==1.84
Requires-Dist: blosum~=2.0
Requires-Dist: click~=8.1
Requires-Dist: psutil~=5.9
Requires-Dist: python-dotenv~=1.0
Requires-Dist: scikit-bio==0.6.2
Requires-Dist: scipy~=1.9
Requires-Dist: tqdm~=4.66
Requires-Dist: cachetools>=5.5.2,<6.0.0
License-File: LICENSE.txt
Summary: Antibody numbering software
Author: NaturalAntibody
Requires-Python: >=3.10, <4.0
Project-URL: Homepage, https://github.com/NaturalAntibody/riot_na
